<?xml version="1.0" encoding="utf-8"?>
<odoo>
    <data>
        <record id="dashboard_form_view" model="ir.ui.view">
            <field name="name">Dashboard Form</field>
            <field name="model">board.board</field>
            <field name="type">form</field>
            <field name="arch" type="xml">
                <form string="Dashboard">
                    <board style="1-2">
                        <column>
                            <!-- views will come here -->
                        </column>
                        <column>


                        </column>
                    </board>
                </form>
            </field>
        </record>

    </data>
</odoo>